eufy_security/__init__.py
eufy_security/__version__.py
eufy_security/api.py
eufy_security/camera.py
eufy_security/cameras/indoor_cam.py
eufy_security/errors.py
eufy_security/parameters/detection.py
eufy_security/parameters/global_params.py
eufy_security/parameters/notification_params.py
eufy_security/parameters/video_params.py
eufy_security/params.py
python_eufy_security_rik-0.4.0.dist-info/LICENSE
python_eufy_security_rik-0.4.0.dist-info/WHEEL
python_eufy_security_rik-0.4.0.dist-info/METADATA
python_eufy_security_rik-0.4.0.dist-info/RECORD
