Metadata-Version: 2.1
Name: python-eufy-security-rik
Version: 0.4.0
Summary: A Python library for Eufy Security devices
Home-page: https://github.com/FuzzyMistborn/python-eufy-security
License: MIT
Author: Rik Bruggink
Author-email: mail@rikbruggink.nl
Requires-Python: >=3.6.1,<4.0.0
Classifier: License :: OSI Approved :: MIT License
Classifier: Programming Language :: Python
Classifier: Programming Language :: Python :: 3
Classifier: Programming Language :: Python :: 3.6
Classifier: Programming Language :: Python :: 3.7
Classifier: Programming Language :: Python :: 3.8
Classifier: Programming Language :: Python :: Implementation :: CPython
Classifier: Programming Language :: Python :: Implementation :: PyPy
Requires-Dist: aiohttp (==3.6.1)
Project-URL: Repository, https://github.com/FuzzyMistborn/python-eufy-security
